awslabs/__init__.py
awslabs/aws_msk_mcp_server/__init__.py
awslabs/aws_msk_mcp_server/server.py
awslabs/aws_msk_mcp_server/tools/__init__.py
awslabs/aws_msk_mcp_server/tools/common_functions/__init__.py
awslabs/aws_msk_mcp_server/tools/common_functions/client_manager.py
awslabs/aws_msk_mcp_server/tools/common_functions/common_functions.py
awslabs/aws_msk_mcp_server/tools/logs_and_telemetry/__init__.py
awslabs/aws_msk_mcp_server/tools/logs_and_telemetry/cluster_metrics_tools.py
awslabs/aws_msk_mcp_server/tools/logs_and_telemetry/list_customer_iam_access.py
awslabs/aws_msk_mcp_server/tools/logs_and_telemetry/metric_config.py
awslabs/aws_msk_mcp_server/tools/mutate_cluster/__init__.py
awslabs/aws_msk_mcp_server/tools/mutate_cluster/batch_associate_scram_secret.py
awslabs/aws_msk_mcp_server/tools/mutate_cluster/batch_disassociate_scram_secret.py
awslabs/aws_msk_mcp_server/tools/mutate_cluster/create_cluster_v2.py
awslabs/aws_msk_mcp_server/tools/mutate_cluster/put_cluster_policy.py
awslabs/aws_msk_mcp_server/tools/mutate_cluster/reboot_broker.py
awslabs/aws_msk_mcp_server/tools/mutate_cluster/update_broker_count.py
awslabs/aws_msk_mcp_server/tools/mutate_cluster/update_broker_storage.py
awslabs/aws_msk_mcp_server/tools/mutate_cluster/update_broker_type.py
awslabs/aws_msk_mcp_server/tools/mutate_cluster/update_cluster_configuration.py
awslabs/aws_msk_mcp_server/tools/mutate_cluster/update_monitoring.py
awslabs/aws_msk_mcp_server/tools/mutate_cluster/update_security.py
awslabs/aws_msk_mcp_server/tools/mutate_config/__init__.py
awslabs/aws_msk_mcp_server/tools/mutate_config/create_configuration.py
awslabs/aws_msk_mcp_server/tools/mutate_config/tag_resource.py
awslabs/aws_msk_mcp_server/tools/mutate_config/untag_resource.py
awslabs/aws_msk_mcp_server/tools/mutate_config/update_configuration.py
awslabs/aws_msk_mcp_server/tools/mutate_vpc/__init__.py
awslabs/aws_msk_mcp_server/tools/mutate_vpc/create_vpc_connection.py
awslabs_aws_msk_mcp_server-0.0.12.dist-info/METADATA
awslabs_aws_msk_mcp_server-0.0.12.dist-info/WHEEL
awslabs_aws_msk_mcp_server-0.0.12.dist-info/entry_points.txt
awslabs_aws_msk_mcp_server-0.0.12.dist-info/licenses/LICENSE
awslabs_aws_msk_mcp_server-0.0.12.dist-info/licenses/NOTICE
awslabs_aws_msk_mcp_server-0.0.12.dist-info/RECORD
